oss-licenses.json
wagtailmdx/__init__.py
wagtailmdx/apps.py
wagtailmdx/fields.py
wagtailmdx/widgets.py
wagtailmdx/static/wagtailmdx/css/main.css
wagtailmdx/static/wagtailmdx/js/434.mdx.js
wagtailmdx/static/wagtailmdx/js/mdx.js
wagtailmdx/static/wagtailmdx/js/mdx.js.LICENSE.txt
wagtailmdx-0.1.1.dist-info/LICENSE
wagtailmdx-0.1.1.dist-info/METADATA
wagtailmdx-0.1.1.dist-info/WHEEL
wagtailmdx-0.1.1.dist-info/top_level.txt
wagtailmdx-0.1.1.dist-info/RECORD
